pdfdeal/__init__.py
pdfdeal/doc2x.py
pdfdeal/doc2x_legacy.py
pdfdeal/file_tools.py
pdfdeal/CLI/doc2x.py
pdfdeal/Doc2X/ConvertV1.py
pdfdeal/Doc2X/ConvertV2.py
pdfdeal/Doc2X/Exception.py
pdfdeal/Doc2X/Pages.py
pdfdeal/Doc2X/Types.py
pdfdeal/FileTools/dealmd.py
pdfdeal/FileTools/dealpdfs.py
pdfdeal/FileTools/extract_img.py
pdfdeal/FileTools/file_tools.py
pdfdeal/FileTools/html2md.py
pdfdeal/FileTools/Img/Ali_OSS.py
pdfdeal/FileTools/Img/MinIO.py
pdfdeal/FileTools/Img/PicGO.py
pdfdeal/FileTools/Img/S3.py
pdfdeal/Watch/config.py
pdfdeal/Watch/connect.py
pdfdeal/Watch/i18n.py
pdfdeal/Watch/store.py
pdfdeal/Watch/work.py
pdfdeal/Watch/Connect/local.py
pdfdeal-1.0.2.dist-info/METADATA
pdfdeal-1.0.2.dist-info/WHEEL
pdfdeal-1.0.2.dist-info/entry_points.txt
pdfdeal-1.0.2.dist-info/licenses/LICENSE
pdfdeal-1.0.2.dist-info/RECORD
