Metadata-Version: 2.4
Name: pdfdeal
Version: 1.0.2
Summary: A python wrapper for the Doc2X API and comes with native texts processing (to improve texts recall in RAG).
Project-URL: Issues, https://github.com/Menghuan1918/pdfdeal/issues
Project-URL: Documentation, https://menghuan1918.github.io/pdfdeal-docs/
Project-URL: Source, https://github.com/Menghuan1918/pdfdeal
Project-URL: Changelog, https://menghuan1918.github.io/pdfdeal-docs/changes/
Author-email: Menghuan1918 <menghuan@menghuan1918.com>
License-File: LICENSE
Classifier: License :: OSI Approved :: MIT License
Classifier: Operating System :: OS Independent
Classifier: Programming Language :: Python :: 3
Requires-Python: >=3.8
Requires-Dist: httpx[http2]<1,>=0.23.1
Requires-Dist: pypdf
Provides-Extra: dev
Requires-Dist: beautifulsoup4; extra == 'dev'
Requires-Dist: boto3; extra == 'dev'
Requires-Dist: emoji; extra == 'dev'
Requires-Dist: minio; extra == 'dev'
Requires-Dist: oss2; extra == 'dev'
Requires-Dist: pillow; extra == 'dev'
Requires-Dist: pytest; extra == 'dev'
Requires-Dist: reportlab; extra == 'dev'
Provides-Extra: rag
Requires-Dist: beautifulsoup4; extra == 'rag'
Requires-Dist: boto3; extra == 'rag'
Requires-Dist: emoji; extra == 'rag'
Requires-Dist: minio; extra == 'rag'
Requires-Dist: oss2; extra == 'rag'
Requires-Dist: pillow; extra == 'rag'
Requires-Dist: reportlab; extra == 'rag'
Provides-Extra: tools
Requires-Dist: beautifulsoup4; extra == 'tools'
Requires-Dist: emoji; extra == 'tools'
Requires-Dist: pillow; extra == 'tools'
Requires-Dist: reportlab; extra == 'tools'
